[
  {
    "id": "asset_a0000001",
    "name": "ERP-System (SAP S/4HANA)",
    "category": "software",
    "type": "software_saas",
    "description": "Zentrales ERP-System für Finanzbuchhaltung, Controlling, Beschaffung und Produktion. Betrieb als SaaS über SAP Business Technology Platform.",
    "owner": "Claudia Meier",
    "ownerEmail": "claudia.meier@konzern.de",
    "custodian": "IT-Betrieb / ERP-Team",
    "entityId": "",
    "location": "SAP BTP EU10 (Frankfurt)",
    "classification": "confidential",
    "criticality": "critical",
    "status": "active",
    "vendor": "SAP SE",
    "version": "S/4HANA 2023",
    "serialNumber": "",
    "purchaseDate": "2022-01-01",
    "endOfLifeDate": "2030-12-31",
    "tags": ["erp", "sap", "finanzen", "produktion"],
    "notes": "Kritisches System – SLA 99,9 % vereinbart. Notfallplan vorhanden.",
    "createdAt": "2025-06-01T08:00:00.000Z",
    "updatedAt": "2025-06-01T08:00:00.000Z",
    "createdBy": "system"
  },
  {
    "id": "asset_a0000002",
    "name": "Produktionsserver Werk 1",
    "category": "hardware",
    "type": "hardware_server",
    "description": "Physischer Rack-Server für Produktionssteuerung und MES-System in Werk Dortmund. Redundant ausgelegt (Cluster mit Backup-NAS).",
    "owner": "Thomas Becker",
    "ownerEmail": "thomas.becker@konzern.de",
    "custodian": "IT-Infrastruktur / Werk 1",
    "entityId": "",
    "location": "Serverraum Werk 1, Schrank A-03",
    "classification": "confidential",
    "criticality": "critical",
    "status": "active",
    "vendor": "HPE",
    "version": "ProLiant DL380 Gen10",
    "serialNumber": "SRV-WK1-2021-001",
    "purchaseDate": "2021-03-15",
    "endOfLifeDate": "2026-03-31",
    "tags": ["server", "mes", "produktion", "werk1"],
    "notes": "Wartungsvertrag bis 2026. EoL-Evaluierung Q4/2025 geplant.",
    "createdAt": "2025-06-01T08:00:00.000Z",
    "updatedAt": "2025-06-01T08:00:00.000Z",
    "createdBy": "system"
  },
  {
    "id": "asset_a0000003",
    "name": "ICS-Steuerungsanlage Linie 1",
    "category": "hardware",
    "type": "hardware_ics_ot",
    "description": "Siemens SIMATIC S7-1500 SPS für die Steuerung der Fertigungslinie 1 im Werk Dortmund. Netzwerksegmentiert (OT-DMZ). Patch-Zyklus: 12 Wochen.",
    "owner": "Klaus Richter",
    "ownerEmail": "klaus.richter@konzern.de",
    "custodian": "OT-Security / Automatisierungstechnik",
    "entityId": "",
    "location": "Halle 3, Steuerungsschrank S1-07",
    "classification": "confidential",
    "criticality": "critical",
    "status": "active",
    "vendor": "Siemens AG",
    "version": "SIMATIC S7-1500 FW 2.9",
    "serialNumber": "ICS-L1-SPS-2020-001",
    "purchaseDate": "2020-07-01",
    "endOfLifeDate": "2027-06-30",
    "tags": ["ics", "ot", "sps", "siemens", "produktion"],
    "notes": "IEC 62443 Anforderungen anwendbar. Netzwerksegmentierung gemäß OT-Sicherheitskonzept.",
    "createdAt": "2025-06-01T08:00:00.000Z",
    "updatedAt": "2025-06-01T08:00:00.000Z",
    "createdBy": "system"
  },
  {
    "id": "asset_a0000004",
    "name": "Gebäudeleittechnik (GLT) Hauptverwaltung",
    "category": "hardware",
    "type": "hardware_building",
    "description": "Zentrales Gebäudemanagementsystem (BMS/GLT) der Hauptverwaltung. Steuert HLK, Zutritt, Brandmeldeanlage und Beleuchtung.",
    "owner": "Sandra Hoffmann",
    "ownerEmail": "sandra.hoffmann@konzern.de",
    "custodian": "Facility Management",
    "entityId": "",
    "location": "Hauptverwaltung, Technikraum EG",
    "classification": "internal",
    "criticality": "high",
    "status": "active",
    "vendor": "Siemens Building Technologies",
    "version": "Desigo CC 5.0",
    "serialNumber": "GLT-HV-2019-001",
    "purchaseDate": "2019-04-10",
    "endOfLifeDate": "2026-12-31",
    "tags": ["bms", "glt", "gebäude", "hlk", "zutritt"],
    "notes": "Netzwerkisolierung vom IT-Netz empfohlen. Jährliche Überprüfung durch Hersteller.",
    "createdAt": "2025-06-01T08:00:00.000Z",
    "updatedAt": "2025-06-01T08:00:00.000Z",
    "createdBy": "system"
  },
  {
    "id": "asset_a0000005",
    "name": "Active Directory / LDAP",
    "category": "software",
    "type": "software_app",
    "description": "Microsoft Active Directory Domain Services und LDAP-Verzeichnis für die gesamte Konzernstruktur. Zentrale Identitäts- und Zugriffsverwaltung (IAM).",
    "owner": "Markus Schneider",
    "ownerEmail": "markus.schneider@konzern.de",
    "custodian": "IT-Security / IAM-Team",
    "entityId": "",
    "location": "Rechenzentrum Frankfurt, Zone A (redundant)",
    "classification": "strictly_confidential",
    "criticality": "critical",
    "status": "active",
    "vendor": "Microsoft",
    "version": "Windows Server 2022 / AD DS",
    "serialNumber": "",
    "purchaseDate": "2018-09-01",
    "endOfLifeDate": "2031-10-14",
    "tags": ["iam", "active-directory", "ldap", "identität", "zugriff"],
    "notes": "Tier-0-Asset. Privilegierte Zugriffe ausschließlich über PAM-System. Quarterly Review.",
    "createdAt": "2025-06-01T08:00:00.000Z",
    "updatedAt": "2025-06-01T08:00:00.000Z",
    "createdBy": "system"
  },
  {
    "id": "asset_a0000006",
    "name": "Produktionsstätte Werk 1 Dortmund",
    "category": "facility",
    "type": "facility_production",
    "description": "Produktionswerk Dortmund-Nord mit 5 Fertigungslinien. Fläche 12.000 m². Zutrittsschutz über Kartensystem (Zone 1–3).",
    "owner": "Hans-Jörg Weber",
    "ownerEmail": "hans-joerg.weber@konzern.de",
    "custodian": "Facility Management / Werkleitung",
    "entityId": "",
    "location": "Industriestraße 42, 44145 Dortmund",
    "classification": "internal",
    "criticality": "high",
    "status": "active",
    "vendor": "",
    "version": "",
    "serialNumber": "",
    "purchaseDate": "2005-01-01",
    "endOfLifeDate": "",
    "tags": ["werk", "produktion", "dortmund", "facility"],
    "notes": "Notfallplan Werk 1 aktuell. Letzte Begehung: 2025-01-15. Nächste geplant: 2025-07-01.",
    "createdAt": "2025-06-01T08:00:00.000Z",
    "updatedAt": "2025-06-01T08:00:00.000Z",
    "createdBy": "system"
  },
  {
    "id": "asset_a0000007",
    "name": "Kundendatenbank CRM",
    "category": "data",
    "type": "data_database",
    "description": "PostgreSQL-Datenbank mit Kundenstammdaten, Verkaufshistorie und Kontaktdaten. Ca. 850.000 Datensätze, davon 240.000 mit personenbezogenen Daten (DSGVO-relevant).",
    "owner": "Julia Brandt",
    "ownerEmail": "julia.brandt@konzern.de",
    "custodian": "IT-Betrieb / Datenbankteam",
    "entityId": "",
    "location": "Rechenzentrum Frankfurt, Zone B",
    "classification": "strictly_confidential",
    "criticality": "critical",
    "status": "active",
    "vendor": "Open-Source (PostgreSQL)",
    "version": "PostgreSQL 16",
    "serialNumber": "",
    "purchaseDate": "",
    "endOfLifeDate": "",
    "tags": ["crm", "kundendaten", "dsgvo", "datenbank", "postgresql"],
    "notes": "VVT-Eintrag vorhanden (Art. 30 DSGVO). Verschlüsselung at-rest und in-transit aktiviert. Backup täglich.",
    "createdAt": "2025-06-01T08:00:00.000Z",
    "updatedAt": "2025-06-01T08:00:00.000Z",
    "createdBy": "system"
  },
  {
    "id": "asset_a0000008",
    "name": "Backup-NAS Rechenzentrum Frankfurt",
    "category": "hardware",
    "type": "hardware_other",
    "description": "Synology NAS-System für zentrales Backup aller kritischen Server und Datenbanken. 3-2-1-Backup-Strategie. Tägliche inkrementelle, wöchentliche Vollsicherung.",
    "owner": "Markus Schneider",
    "ownerEmail": "markus.schneider@konzern.de",
    "custodian": "IT-Betrieb / Backup-Team",
    "entityId": "",
    "location": "Rechenzentrum Frankfurt, Zone C, Rack C-12",
    "classification": "confidential",
    "criticality": "high",
    "status": "active",
    "vendor": "Synology",
    "version": "DiskStation DS3622xs+, DSM 7.2",
    "serialNumber": "NAS-RZ-FRA-2022-001",
    "purchaseDate": "2022-06-01",
    "endOfLifeDate": "2029-06-30",
    "tags": ["backup", "nas", "synology", "datensicherung"],
    "notes": "Restore-Tests monatlich. Offsite-Kopie in Sekundär-RZ Berlin. Verschlüsselung aktiviert.",
    "createdAt": "2025-06-01T08:00:00.000Z",
    "updatedAt": "2025-06-01T08:00:00.000Z",
    "createdBy": "system"
  },
  {
    "id": "asset_a0000009",
    "name": "Firewall-Cluster (Perimeter)",
    "category": "hardware",
    "type": "hardware_network",
    "description": "Fortinet FortiGate HA-Cluster als zentrale Perimeter-Firewall des Konzerns. Trennt Internet, DMZ und internes Netz. NGFW mit IPS/IDS und SSL-Inspection.",
    "owner": "Markus Schneider",
    "ownerEmail": "markus.schneider@konzern.de",
    "custodian": "IT-Security / Netzwerkteam",
    "entityId": "",
    "location": "Rechenzentrum Frankfurt, Zone A, Rack A-01/A-02",
    "classification": "confidential",
    "criticality": "critical",
    "status": "active",
    "vendor": "Fortinet",
    "version": "FortiGate 600F, FortiOS 7.4",
    "serialNumber": "FW-RZ-FRA-2023-001",
    "purchaseDate": "2023-02-01",
    "endOfLifeDate": "2028-02-28",
    "tags": ["firewall", "netzwerk", "perimeter", "fortinet", "ngfw"],
    "notes": "HA-Cluster aktiv/passiv. Failover-Zeit < 10 s. Jährlicher Penetrationstest.",
    "createdAt": "2025-06-01T08:00:00.000Z",
    "updatedAt": "2025-06-01T08:00:00.000Z",
    "createdBy": "system"
  },
  {
    "id": "asset_a0000010",
    "name": "Core-Switch Rechenzentrum Frankfurt",
    "category": "hardware",
    "type": "hardware_network",
    "description": "Cisco Nexus Core-Switch-Stack im zentralen Rechenzentrum Frankfurt. Backbone für alle Server-VLANs, Speichernetzwerk und Management-Netz.",
    "owner": "Thomas Becker",
    "ownerEmail": "thomas.becker@konzern.de",
    "custodian": "IT-Infrastruktur / Netzwerkteam",
    "entityId": "",
    "location": "Rechenzentrum Frankfurt, Zone A, Rack A-10",
    "classification": "internal",
    "criticality": "critical",
    "status": "active",
    "vendor": "Cisco Systems",
    "version": "Nexus 9300, NX-OS 10.3",
    "serialNumber": "SW-RZ-FRA-2021-001",
    "purchaseDate": "2021-08-15",
    "endOfLifeDate": "2028-08-31",
    "tags": ["switch", "netzwerk", "cisco", "core", "rechenzentrum"],
    "notes": "Redundante Uplinks zu Perimeter-Firewall und WAN-Router. SNMP-Monitoring aktiv.",
    "createdAt": "2025-06-01T08:00:00.000Z",
    "updatedAt": "2025-06-01T08:00:00.000Z",
    "createdBy": "system"
  },
  {
    "id": "asset_a0000011",
    "name": "Laptop-Fleet Außendienst (250 Geräte)",
    "category": "hardware",
    "type": "hardware_laptop",
    "description": "Standardisierter Laptop-Pool für den Außendienst. Lenovo ThinkPad E-Serie, verwaltet über Microsoft Endpoint Manager (Intune). BitLocker-Verschlüsselung, MDM-Richtlinien.",
    "owner": "Claudia Meier",
    "ownerEmail": "claudia.meier@konzern.de",
    "custodian": "IT-Workplace / Endpunkt-Management",
    "entityId": "",
    "location": "Dezentral (Außendienst bundesweit)",
    "classification": "internal",
    "criticality": "medium",
    "status": "active",
    "vendor": "Lenovo",
    "version": "ThinkPad E15 Gen 4, Windows 11 Pro",
    "serialNumber": "FLEET-LAP-2023",
    "purchaseDate": "2023-01-01",
    "endOfLifeDate": "2027-12-31",
    "tags": ["laptop", "endpunkt", "außendienst", "intune", "bitlocker"],
    "notes": "Leasing-Modell über DLL. 3-Jahres-Zyklus. Verlorene Geräte: Remote-Wipe über Intune.",
    "createdAt": "2025-06-01T08:00:00.000Z",
    "updatedAt": "2025-06-01T08:00:00.000Z",
    "createdBy": "system"
  },
  {
    "id": "asset_a0000012",
    "name": "Smartphones Konzernflotte (180 Geräte)",
    "category": "hardware",
    "type": "hardware_mobile",
    "description": "Samsung Galaxy S-Serie für Führungskräfte und Außendienst. Verwaltet über VMware Workspace ONE. Container-Lösung trennt geschäftliche und private Daten.",
    "owner": "Claudia Meier",
    "ownerEmail": "claudia.meier@konzern.de",
    "custodian": "IT-Workplace / Mobile-Team",
    "entityId": "",
    "location": "Dezentral (bundesweit)",
    "classification": "internal",
    "criticality": "medium",
    "status": "active",
    "vendor": "Samsung / VMware",
    "version": "Galaxy S24, Android 14, Workspace ONE",
    "serialNumber": "FLEET-MOB-2024",
    "purchaseDate": "2024-01-01",
    "endOfLifeDate": "2026-12-31",
    "tags": ["smartphone", "mobil", "mdm", "workspace-one"],
    "notes": "BYOD nicht erlaubt. 2-Jahres-Zyklus. Remote-Wipe bei Verlust.",
    "createdAt": "2025-06-01T08:00:00.000Z",
    "updatedAt": "2025-06-01T08:00:00.000Z",
    "createdBy": "system"
  },
  {
    "id": "asset_a0000013",
    "name": "Microsoft 365 (E3-Lizenzierung)",
    "category": "software",
    "type": "software_saas",
    "description": "Microsoft 365 E3 für alle Konzernmitarbeiter: Exchange Online, Teams, SharePoint, OneDrive, Office-Apps. Datenhaltung EU (Niederlande). DLP-Richtlinien konfiguriert.",
    "owner": "Claudia Meier",
    "ownerEmail": "claudia.meier@konzern.de",
    "custodian": "IT-Workplace / Cloud-Team",
    "entityId": "",
    "location": "Microsoft Azure EU North (Amsterdam)",
    "classification": "confidential",
    "criticality": "high",
    "status": "active",
    "vendor": "Microsoft",
    "version": "Microsoft 365 E3",
    "serialNumber": "",
    "purchaseDate": "2021-04-01",
    "endOfLifeDate": "",
    "tags": ["m365", "teams", "exchange", "sharepoint", "cloud", "saas"],
    "notes": "Tenant-ID dokumentiert. Conditional Access aktiviert. MFA für alle Benutzer Pflicht. AV-Vertrag mit Microsoft vorhanden (DSGVO).",
    "createdAt": "2025-06-01T08:00:00.000Z",
    "updatedAt": "2025-06-01T08:00:00.000Z",
    "createdBy": "system"
  },
  {
    "id": "asset_a0000014",
    "name": "ICS-Steuerungsanlage Linie 2",
    "category": "hardware",
    "type": "hardware_ics_ot",
    "description": "ABB AC500 SPS für Fertigungslinie 2 (Montage). Vernetzt mit SCADA-System über OPC-UA. Netzwerksegmentiert gemäß Purdue-Modell Level 1.",
    "owner": "Klaus Richter",
    "ownerEmail": "klaus.richter@konzern.de",
    "custodian": "OT-Security / Automatisierungstechnik",
    "entityId": "",
    "location": "Halle 4, Steuerungsschrank S2-03",
    "classification": "confidential",
    "criticality": "high",
    "status": "active",
    "vendor": "ABB",
    "version": "AC500 PM592, FW 3.3.0",
    "serialNumber": "ICS-L2-SPS-2022-001",
    "purchaseDate": "2022-03-01",
    "endOfLifeDate": "2029-12-31",
    "tags": ["ics", "ot", "abb", "sps", "montage"],
    "notes": "OPC-UA-Kommunikation nur mit SCADA-Server. Keine Verbindung ins IT-Netz.",
    "createdAt": "2025-06-01T08:00:00.000Z",
    "updatedAt": "2025-06-01T08:00:00.000Z",
    "createdBy": "system"
  },
  {
    "id": "asset_a0000015",
    "name": "Personalstammdaten HR (Dokumentenablage)",
    "category": "data",
    "type": "data_document",
    "description": "Digitale Personalakte aller Konzernmitarbeiter: Verträge, Gehaltsabrechnungen, Beurteilungen, Krankmeldungen. Ca. 1.200 aktive Mitarbeiter. DSGVO-kritisch.",
    "owner": "Petra Vogel",
    "ownerEmail": "petra.vogel@konzern.de",
    "custodian": "HR / IT-Betrieb",
    "entityId": "",
    "location": "Rechenzentrum Frankfurt, verschlüsselter Fileserver",
    "classification": "strictly_confidential",
    "criticality": "high",
    "status": "active",
    "vendor": "",
    "version": "",
    "serialNumber": "",
    "purchaseDate": "",
    "endOfLifeDate": "",
    "tags": ["hr", "personalakte", "dsgvo", "vertraulich"],
    "notes": "Zugriff ausschließlich HR-Abteilung + Systemadmin. Löschkonzept gemäß § 35 BDSG. VVT-Eintrag vorhanden.",
    "createdAt": "2025-06-01T08:00:00.000Z",
    "updatedAt": "2025-06-01T08:00:00.000Z",
    "createdBy": "system"
  },
  {
    "id": "asset_a0000016",
    "name": "Backup-Archiv Langzeitsicherung (Tape)",
    "category": "data",
    "type": "data_backup",
    "description": "LTO-9-Tape-Bibliothek für Langzeitsicherung und gesetzlich vorgeschriebene Aufbewahrungsfristen (HGB 10 Jahre). Monatliche Vollsicherung, offline gelagert.",
    "owner": "Markus Schneider",
    "ownerEmail": "markus.schneider@konzern.de",
    "custodian": "IT-Betrieb / Backup-Team",
    "entityId": "",
    "location": "Tresorraum Hauptverwaltung, UG",
    "classification": "confidential",
    "criticality": "medium",
    "status": "active",
    "vendor": "HPE StoreEver",
    "version": "MSL3040 Tape Library, LTO-9",
    "serialNumber": "TAPE-HV-2020-001",
    "purchaseDate": "2020-11-01",
    "endOfLifeDate": "2030-10-31",
    "tags": ["tape", "backup", "langzeit", "archiv", "hgb"],
    "notes": "Tapes beschriftet und inventarisiert. Jährlicher Restore-Test. Brandschutzbox zertifiziert.",
    "createdAt": "2025-06-01T08:00:00.000Z",
    "updatedAt": "2025-06-01T08:00:00.000Z",
    "createdBy": "system"
  },
  {
    "id": "asset_a0000017",
    "name": "Rechenzentrum Frankfurt (Primär-RZ)",
    "category": "facility",
    "type": "facility_datacenter",
    "description": "Primäres Rechenzentrum in Frankfurt am Main. Tier-3-zertifiziert, redundante Stromversorgung (USV + Notstromaggregat), Klimatisierung N+1, Zutritt Biometrie + Badge.",
    "owner": "Thomas Becker",
    "ownerEmail": "thomas.becker@konzern.de",
    "custodian": "IT-Infrastruktur / Datacenter-Team",
    "entityId": "",
    "location": "Mainzer Landstraße 55, 60329 Frankfurt am Main",
    "classification": "internal",
    "criticality": "critical",
    "status": "active",
    "vendor": "",
    "version": "",
    "serialNumber": "",
    "purchaseDate": "2010-01-01",
    "endOfLifeDate": "",
    "tags": ["rechenzentrum", "tier3", "frankfurt", "facility"],
    "notes": "ISO 27001 Zertifizierung vorhanden. Jährliche Begehung + Audit. Notfallversorgung 72 h gesichert.",
    "createdAt": "2025-06-01T08:00:00.000Z",
    "updatedAt": "2025-06-01T08:00:00.000Z",
    "createdBy": "system"
  },
  {
    "id": "asset_a0000018",
    "name": "Hauptverwaltung Düsseldorf",
    "category": "facility",
    "type": "facility_office",
    "description": "Konzernhauptverwaltung in Düsseldorf. 6 Etagen, ca. 450 Arbeitsplätze. Zutritt über Chipkartensystem, Videoüberwachung Empfang und Tiefgarage.",
    "owner": "Sandra Hoffmann",
    "ownerEmail": "sandra.hoffmann@konzern.de",
    "custodian": "Facility Management",
    "entityId": "",
    "location": "Königsallee 18, 40212 Düsseldorf",
    "classification": "internal",
    "criticality": "medium",
    "status": "active",
    "vendor": "",
    "version": "",
    "serialNumber": "",
    "purchaseDate": "2000-07-01",
    "endOfLifeDate": "",
    "tags": ["büro", "hauptverwaltung", "düsseldorf", "facility"],
    "notes": "Mietvertrag läuft bis 2032. Klimaanlage Wartungsvertrag mit Thermo-Schäfer GmbH.",
    "createdAt": "2025-06-01T08:00:00.000Z",
    "updatedAt": "2025-06-01T08:00:00.000Z",
    "createdBy": "system"
  },
  {
    "id": "asset_a0000019",
    "name": "Managed SOC (extern)",
    "category": "service",
    "type": "service_external",
    "description": "Externes Security Operations Center durch Telekom Security GmbH. 24/7 SIEM-Monitoring, Incident Detection & Response. SLA: P1-Incidents < 15 min Reaktionszeit.",
    "owner": "Markus Schneider",
    "ownerEmail": "markus.schneider@konzern.de",
    "custodian": "IT-Security",
    "entityId": "",
    "location": "Telekom Security, Bonn (extern)",
    "classification": "confidential",
    "criticality": "high",
    "status": "active",
    "vendor": "Telekom Security GmbH",
    "version": "",
    "serialNumber": "",
    "purchaseDate": "2023-07-01",
    "endOfLifeDate": "2026-06-30",
    "tags": ["soc", "siem", "monitoring", "extern", "security"],
    "notes": "AV-Vertrag (DSGVO Art. 28) vorhanden. Jährliches Service-Review. Log-Daten werden nicht außerhalb der EU gespeichert.",
    "createdAt": "2025-06-01T08:00:00.000Z",
    "updatedAt": "2025-06-01T08:00:00.000Z",
    "createdBy": "system"
  },
  {
    "id": "asset_a0000020",
    "name": "Cloud-Backup (Azure Backup)",
    "category": "service",
    "type": "service_cloud",
    "description": "Microsoft Azure Backup für Off-Site-Sicherung kritischer Systeme. GRS-Redundanz (geo-redundant), Aufbewahrung 90 Tage. Ergänzung zur lokalen NAS-Sicherung.",
    "owner": "Markus Schneider",
    "ownerEmail": "markus.schneider@konzern.de",
    "custodian": "IT-Betrieb / Cloud-Team",
    "entityId": "",
    "location": "Microsoft Azure West Europe (Amsterdam) + Nord Europe (Dublin)",
    "classification": "confidential",
    "criticality": "high",
    "status": "active",
    "vendor": "Microsoft Azure",
    "version": "Azure Backup (MABS v4)",
    "serialNumber": "",
    "purchaseDate": "2023-01-01",
    "endOfLifeDate": "",
    "tags": ["backup", "cloud", "azure", "offsite"],
    "notes": "Verschlüsselung mit kundeneigenem Key (CMK) in Azure Key Vault. Monatlicher Restore-Test. AV-Vertrag Microsoft vorhanden.",
    "createdAt": "2025-06-01T08:00:00.000Z",
    "updatedAt": "2025-06-01T08:00:00.000Z",
    "createdBy": "system"
  },
  {
    "id": "asset_a0000021",
    "name": "IoT-Sensornetz Werk 1 (Predictive Maintenance)",
    "category": "hardware",
    "type": "hardware_ics_ot",
    "description": "Geplantes IoT-Sensornetz für Predictive Maintenance an Fertigungsanlagen Werk 1. Vibrations-, Temperatur- und Stromsensoren. Anbindung über dediziertes IoT-VLAN.",
    "owner": "Klaus Richter",
    "ownerEmail": "klaus.richter@konzern.de",
    "custodian": "OT-Security / Automatisierungstechnik",
    "entityId": "",
    "location": "Halle 3–5, Werk 1 Dortmund",
    "classification": "internal",
    "criticality": "medium",
    "status": "planned",
    "vendor": "Pepperl+Fuchs / AWS IoT",
    "version": "Planung v1.2",
    "serialNumber": "",
    "purchaseDate": "",
    "endOfLifeDate": "",
    "tags": ["iot", "predictive-maintenance", "sensor", "ot", "geplant"],
    "notes": "Sicherheitskonzept in Erstellung (Q2/2026). Netzwerksegmentierung über separates IoT-VLAN geplant.",
    "createdAt": "2025-06-01T08:00:00.000Z",
    "updatedAt": "2025-06-01T08:00:00.000Z",
    "createdBy": "system"
  },
  {
    "id": "asset_a0000022",
    "name": "Altserver Werk 2 (außer Betrieb)",
    "category": "hardware",
    "type": "hardware_server",
    "description": "Dell PowerEdge R730 aus Werk 2 Bochum. Nach Schließung des Standorts 2024 außer Betrieb genommen. Festplatten nach NIST 800-88 sicher gelöscht, Hardware für Entsorgung freigegeben.",
    "owner": "Thomas Becker",
    "ownerEmail": "thomas.becker@konzern.de",
    "custodian": "IT-Infrastruktur",
    "entityId": "",
    "location": "Lager Hauptverwaltung, Raum L-04",
    "classification": "internal",
    "criticality": "low",
    "status": "decommissioned",
    "vendor": "Dell Technologies",
    "version": "PowerEdge R730, Windows Server 2016",
    "serialNumber": "SRV-WK2-2016-003",
    "purchaseDate": "2016-05-01",
    "endOfLifeDate": "2024-06-30",
    "tags": ["server", "decommissioned", "werk2", "entsorgung"],
    "notes": "Datenlöschung protokolliert (Zertifikat vorhanden). Entsorgung über zertifizierten IT-Recycler geplant (Q2/2026).",
    "createdAt": "2025-06-01T08:00:00.000Z",
    "updatedAt": "2025-06-01T08:00:00.000Z",
    "createdBy": "system"
  }
]
